rest_framework/__init__.py
rest_framework/application.py
rest_framework/exceptions.py
rest_framework/filter.py
rest_framework/handler.py
rest_framework/model.py
rest_framework/request.py
rest_framework/response.py
rest_framework/serializer.py
rest_framework/torndb.py
rest_framework/conf/__init__.py
rest_framework/conf/default_config.py
tests/__init__.py
tests/coroutine_test.py
tests/test.py
xx_rest_framework-1.0.1.2.dist-info/METADATA
xx_rest_framework-1.0.1.2.dist-info/WHEEL
xx_rest_framework-1.0.1.2.dist-info/top_level.txt
xx_rest_framework-1.0.1.2.dist-info/RECORD
