Metadata-Version: 2.1
Name: xx-rest-framework
Version: 1.0.1.2
Summary: tornado rest framework
Author: xingxing
Author-email: chenxingyu@ndnu.edu.cn
License: UNKNOWN
Platform: UNKNOWN
Classifier: Programming Language :: Python :: 3
Classifier: License :: OSI Approved :: MIT License
Classifier: Operating System :: OS Independent
Requires-Python: >=3.8
